nhs_context_logging/__init__.py
nhs_context_logging/constants.py
nhs_context_logging/fixtures.py
nhs_context_logging/formatters.py
nhs_context_logging/handlers.py
nhs_context_logging/logger.py
nhs_context_logging/py.typed
nhs_context_logging/utils.py
nhs_context_logging-0.7.1.dist-info/LICENSE.md
nhs_context_logging-0.7.1.dist-info/METADATA
nhs_context_logging-0.7.1.dist-info/WHEEL
nhs_context_logging-0.7.1.dist-info/RECORD
