Metadata-Version: 2.1
Name: nhs-context-logging
Version: 0.7.1
Summary: 
Home-page: https://github.com/NHSDigital/nhs-context-logging
License: GPLv3
Author: spinecore
Requires-Python: >=3.10
Classifier: License :: Other/Proprietary License
Classifier: Programming Language :: Python :: 3
Classifier: Programming Language :: Python :: 3.10
Classifier: Programming Language :: Python :: 3.11
Provides-Extra: pytest
Project-URL: Repository, https://github.com/NHSDigital/nhs-context-logging
